tests/__init__.py
tests/conftest.py
tests/helper.py
tests/test_ttarray.py
tests/core/__init__.py
tests/core/test_io.py
tests/core/contraction/__init__.py
tests/core/contraction/test_dot.py
tests/core/contraction/test_matmul.py
tests/core/contraction/test_tensordot.py
tests/core/creation/__init__.py
tests/core/creation/test_array.py
tests/core/creation/test_array_r1.py
tests/core/creation/test_diag.py
tests/core/creation/test_empty.py
tests/core/creation/test_full.py
tests/core/creation/test_loggeomspace.py
tests/core/creation/test_ones.py
tests/core/creation/test_zeros.py
tests/core/math/__init__.py
tests/core/math/test_add.py
tests/core/math/test_conj.py
tests/core/math/test_multiply.py
tests/raw/__init__.py
tests/raw/test_add.py
tests/raw/test_array_conversion.py
tests/raw/test_canonical.py
tests/raw/test_multiply.py
tests/raw/test_recluster.py
tests/raw/test_svd.py
tests/raw/test_tensordot.py
ttarray/__init__.py
ttarray/core/__init__.py
ttarray/core/array.py
ttarray/core/base.py
ttarray/core/canonicalize.py
ttarray/core/contraction.py
ttarray/core/creation.py
ttarray/core/dispatch.py
ttarray/core/einsum.py
ttarray/core/io.py
ttarray/core/math.py
ttarray/core/reshape.py
ttarray/core/slice.py
ttarray/core/transpose.py
ttarray/core/truncate.py
ttarray/linalg/__init__.py
ttarray/raw/__init__.py
ttarray/raw/add.py
ttarray/raw/array_conversion.py
ttarray/raw/canonical.py
ttarray/raw/contraction.py
ttarray/raw/diag.py
ttarray/raw/multiply.py
ttarray/raw/recluster.py
ttarray/raw/svd.py
ttarray/raw/truncate.py
ttarray-0.0.2.dist-info/LICENSE
ttarray-0.0.2.dist-info/METADATA
ttarray-0.0.2.dist-info/WHEEL
ttarray-0.0.2.dist-info/top_level.txt
ttarray-0.0.2.dist-info/RECORD
