Metadata-Version: 2.1
Name: ttarray
Version: 0.0.2
Summary: Library for tensor train arrays with numpy-compatible api
Home-page: https://github.com/sonnerm/ttarray
Author: Michael Sonner
Author-email: sonnerm@gmail.com
License: MIT
Platform: any
Classifier: Programming Language :: Python :: 3
Classifier: License :: OSI Approved :: MIT License
Classifier: Operating System :: OS Independent
Classifier: Development Status :: 1 - Planning
Requires-Python: >=3.8
License-File: LICENSE
Requires-Dist: numpy (>=1.19.0)
